joj_submitter/__init__.py
joj_submitter/__main__.py
joj_submitter-0.0.10.dist-info/LICENSE.txt
joj_submitter-0.0.10.dist-info/METADATA
joj_submitter-0.0.10.dist-info/WHEEL
joj_submitter-0.0.10.dist-info/entry_points.txt
joj_submitter-0.0.10.dist-info/top_level.txt
joj_submitter-0.0.10.dist-info/RECORD
