Metadata-Version: 2.1
Name: joj-submitter
Version: 0.0.10
Summary: Submit your work to JOJ via cli.
Home-page: https://github.com/BoYanZh/JOJ-Submitter
Author: BoYanZh
Author-email: bomingzh@sjtu.edu.cn
Maintainer: BoYanZh
Maintainer-email: bomingzh@sjtu.edu.cn
License: MIT
Project-URL: Bug Reports, https://github.com/BoYanZh/JOJ-Submitter/issues
Project-URL: Source, https://github.com/BoYanZh/JOJ-Submitter
Requires-Python: >=3.6
License-File: LICENSE.txt
Requires-Dist: beautifulsoup4 (>=4.9.3)
Requires-Dist: pydantic (>=1.8.1)
Requires-Dist: requests (>=2.25.1)
Requires-Dist: typer[all] (>=0.3.2)
